{
  "points": [
    {
      "title": "이것/그것/저것",
      "explanation": "指示代名词。所指的事物离说话者近时用`이것`；离听者近或已说过的，已知道的事物时用`그것`；离说话者和听者都很远时用`저것`。",
      "examples": [
        {
          "korean": "이것은 아주 좋습니다.",
          "chinese": "这个很好。"
        },
        {
          "korean": "그것을 저에게 주십시오.",
          "chinese": "请把那个给我。"
        },
        {
          "korean": "저것은 누구의 모자입니까?",
          "chinese": "那是谁的帽子？"
        }
      ]
    },
    {
      "title": "무엇",
      "explanation": "疑问代名词。用于对不知道的事物或事情进行询问，相当于汉语的“什么”。",
      "examples": [
        {
          "korean": "저것이 무엇입니까?",
          "chinese": "那是什么？"
        },
        {
          "korean": "무엇을 먹었습니까?",
          "chinese": "吃什么了？"
        },
        {
          "korean": "무엇을 좋아합니까?",
          "chinese": "喜欢什么？"
        }
      ]
    },
    {
      "title": "이/가",
      "explanation": "主格助词。跟在体词后表示主语。体词无收音时用`-가`，有收音时用`-이`。第一人称代词`저`, `나`和主格助词`-가`相结合时变为`제가`和`내가`。",
      "table": "| |-이/가|-은/는|-의|\n|---|---|---|---|\n|나|내가|나는|내 (나의)|\n|저|제가|저는|제 (저의)|",
      "examples": [
        {
          "korean": "이것이 연필입니다.",
          "chinese": "这是铅笔。"
        },
        {
          "korean": "그분이 우리 어머니입니다.",
          "chinese": "那位是我妈妈。"
        },
        {
          "korean": "제가 영화표를 사겠습니다.",
          "chinese": "我来买电影票。"
        }
      ]
    },
    {
      "title": "의",
      "explanation": "表示所有或所属的助词。口语当中常省略。第一人称代词的所有格`저의`一般用为`제`, `우리의`一般用为`우리`。",
      "examples": [
        {
          "korean": "이것은 민수 씨의 공책입니다.",
          "chinese": "这是敏秀的本子。"
        },
        {
          "korean": "이 사람은 제 친구입니다.",
          "chinese": "这是我的朋友。"
        },
        {
          "korean": "여기가 우리 교실입니다.",
          "chinese": "这里是我们的教室。"
        }
      ]
    },
    {
      "title": "이/가 아니다",
      "explanation": "是`-이다`的否定式，常与主格助词`-이/가`结合，以`-이/가 아니다`的形式使用。",
      "examples": [
        {
          "korean": "저는 의사가 아닙니다.",
          "chinese": "我不是医生。"
        },
        {
          "korean": "여기는 부산이 아닙니다.",
          "chinese": "这里不是釜山。"
        },
        {
          "korean": "이것은 교과서가 아닙니다. 사전입니다.",
          "chinese": "这不是教科书。是词典。"
        }
      ]
    }
  ]
}