{
  "points": [
    {
      "title": "-(으)ㄴ 일 이 있다/없다",
      "explanation": "与动词词干结合表示曾经历其种事实与否。口语当中常用以‘-(으)ㄴ 적이 있다/없다’的形态。",
      "examples": [
        {
          "korean": "한국에서 여행을 가 본 일이 있으세요?",
          "chinese": "在韩国旅游过吗？"
        },
        {
          "korean": "유명한 사람을 만난 일이 없습니다.",
          "chinese": "我没见过名人。"
        },
        {
          "korean": "여행 가서 길을 잃은 적이 있습니다.",
          "chinese": "旅游的时候迷过路。"
        }
      ]
    },
    {
      "title": "-밖에",
      "explanation": "表示范围限制的助词，通常用于否定形式。",
      "examples": [
        {
          "korean": "냉장고에 주스밖에 없어요.",
          "chinese": "冰箱里只有果汁。"
        },
        {
          "korean": "집에서 학교까지 10분밖에 걸리지 않습니다.",
          "chinese": "从家到学校只要10分钟。"
        },
        {
          "korean": "이 책을 아직 조금밖에 못 읽었습니다.",
          "chinese": "这本书只读了一点点。"
        }
      ]
    }
  ]
}